vibrav/__init__.py
vibrav/_version.py
vibrav/base.py
vibrav/adf/__init__.py
vibrav/adf/output.py
vibrav/adf/tests/test_adf_output.py
vibrav/core/__init__.py
vibrav/core/config.py
vibrav/core/tests/test_config.py
vibrav/molcas/__init__.py
vibrav/molcas/output.py
vibrav/molcas/tests/test_molcas_output.py
vibrav/numerical/__init__.py
vibrav/numerical/boltzmann.py
vibrav/numerical/degeneracy.py
vibrav/numerical/derivatives.py
vibrav/numerical/frequencies.py
vibrav/numerical/phases.py
vibrav/numerical/redmass.py
vibrav/numerical/vibronic_func.py
vibrav/numerical/vroa_func.py
vibrav/numerical/tests/test_boltzmann.py
vibrav/numerical/tests/test_degeneracy.py
vibrav/numerical/tests/test_derivatives.py
vibrav/numerical/tests/test_redmass.py
vibrav/numerical/tests/test_vibronic_func.py
vibrav/static/adf/ch4/adf-ch4-atom.csv.xz
vibrav/static/adf/ch4/adf-ch4-freq.t21.ascii.xz
vibrav/static/adf/ch4/adf-ch4-frequency.csv.xz
vibrav/static/adf/ethane/adf-ethane-atom.csv.xz
vibrav/static/adf/ethane/adf-ethane-frequency.csv.xz
vibrav/static/adf/ethane/adf-ethane-ts-freq.t21.ascii.xz
vibrav/static/adf/ubr6-1minus/adf-ubr-1minus-b3lyp-numeric-norm-modes-cart.csv.xz
vibrav/static/adf/ubr6-1minus/adf-ubr-1minus-b3lyp-numeric-norm-modes-mwc.csv.xz
vibrav/static/adf/ubr6-1minus/adf-ubr-1minus-b3lyp-numeric-redmass.txt.xz
vibrav/static/adf/ubr6-1minus/adf-ubr-1minus-pbe-numeric-norm-modes-cart.csv.xz
vibrav/static/adf/ubr6-1minus/adf-ubr-1minus-pbe-numeric-norm-modes-mwc.csv.xz
vibrav/static/adf/ubr6-1minus/adf-ubr-1minus-pbe-numeric-redmass.txt.xz
vibrav/static/gaussian/nitromalonamide/g16-nitromalonamide-freq.out.xz
vibrav/static/misc/h2o2-normal-modes.csv.bz2
vibrav/static/misc/boltzmann-tests/boltz-dist-full-test.csv.xz
vibrav/static/misc/displacements/h-atom.csv
vibrav/static/misc/displacements/h2-atom.csv
vibrav/static/misc/displacements/h2-atom_order.dat
vibrav/static/misc/displacements/h2-cart-disps.csv
vibrav/static/misc/displacements/h2-delta.dat
vibrav-0.1.2.dist-info/LICENSE
vibrav-0.1.2.dist-info/METADATA
vibrav-0.1.2.dist-info/WHEEL
vibrav-0.1.2.dist-info/top_level.txt
vibrav-0.1.2.dist-info/RECORD
