Metadata-Version: 2.1
Name: vibrav
Version: 0.1.2
Author: Herbert D Ludowieg
Author-email: herbertl@buffalo.edu
License: LGPLv3
License-File: LICENSE
